chat_toolkit/__init__.py
chat_toolkit/__main__.py
chat_toolkit/common/__init__.py
chat_toolkit/common/constants.py
chat_toolkit/common/custom_types.py
chat_toolkit/common/exceptions.py
chat_toolkit/common/key_tracker.py
chat_toolkit/common/orchestrator.py
chat_toolkit/common/utils.py
chat_toolkit/components/__init__.py
chat_toolkit/components/chatbots/chatbot_component_base.py
chat_toolkit/components/chatbots/openai_chatbot.py
chat_toolkit/components/component_base.py
chat_toolkit/components/speech_to_text/openai_speech_to_text.py
chat_toolkit/components/speech_to_text/speech_to_text_component_base.py
chat_toolkit/components/text_to_speech/pyttsx3_text_to_speech.py
chat_toolkit/components/text_to_speech/text_to_speech_component_base.py
chat_toolkit-1.1.1.dist-info/LICENSE
chat_toolkit-1.1.1.dist-info/METADATA
chat_toolkit-1.1.1.dist-info/WHEEL
chat_toolkit-1.1.1.dist-info/RECORD
