Metadata-Version: 2.1
Name: chat-toolkit
Version: 1.1.1
Summary: Extensible package for creating machine learning powered chatbots.
Home-page: https://github.com/danb27/chat-toolkit
License: MIT
Keywords: chatbot,chatgpt,conversational AI
Author: danb27
Author-email: danbianchini@outlook.com
Requires-Python: >=3.9,<4.0
Classifier: License :: OSI Approved :: MIT License
Classifier: Programming Language :: Python :: 3
Classifier: Programming Language :: Python :: 3.9
Classifier: Programming Language :: Python :: 3.10
Classifier: Programming Language :: Python :: 3.11
Requires-Dist: keyboard (>=0.13.5,<0.14.0)
Requires-Dist: loguru (>=0.6.0,<0.7.0)
Requires-Dist: numpy (>=1.24.2,<2.0.0)
Requires-Dist: openai (>=0.27,<0.28)
Requires-Dist: pytest-cov (>=4.0.0,<5.0.0)
Requires-Dist: pyttsx3 (>=2.90,<3.0)
Requires-Dist: pyxhook (>=1.0.0,<2.0.0)
Requires-Dist: sounddevice (>=0.4,<0.5)
Requires-Dist: soundfile (>=0.12,<0.13)
